server/__init__.py
server/cli.py
server/api/__init__.py
server/api/ipc/__init__.py
server/api/ipc/interface.py
server/api/ipc/none.py
server/api/ipc/spi.py
server/api/v1/__init__.py
server/api/v1/description.md
server/api/v1/endpoints.py
server/api/v1/data_models/__init__.py
server/api/v1/data_models/constants.py
server/api/v1/data_models/digital_ios.py
uhil_api_server-0.1.1.dist-info/METADATA
uhil_api_server-0.1.1.dist-info/WHEEL
uhil_api_server-0.1.1.dist-info/entry_points.txt
uhil_api_server-0.1.1.dist-info/top_level.txt
uhil_api_server-0.1.1.dist-info/RECORD
