Metadata-Version: 2.1
Name: uhil-api-server
Version: 0.1.1
Summary: µHIL API server package
Author-email: Guillaume Sottas <guillaumesottas@gmail.com>
License: BSD License
Project-URL: Repository, https://github.com/Sauci/uhil-api-server
Classifier: Programming Language :: Python :: 3
Classifier: License :: OSI Approved :: BSD License
Classifier: Operating System :: Microsoft :: Windows
Classifier: Operating System :: Unix
Requires-Python: >=3.10
Requires-Dist: pydantic~=2.8.2
Requires-Dist: fastapi~=0.115.5
Requires-Dist: spidev~=3.6; sys_platform != "win32"
Requires-Dist: starlette~=0.41.3
Requires-Dist: starlette_context
Requires-Dist: argparse~=1.4.0
Requires-Dist: uvicorn~=0.32.1
